<?xml version="1.0" encoding="utf-8"?>
<UserData xmlns:xsd="http://www.w3.org/2001/XMLSchema" xmlns:xsi="http://www.w3.org/2001/XMLSchema-instance">
  <GameType>Singleplayer</GameType>
  <SingleplayerData>
    <ModDatas>
      <UserModData>
        <Id>Bannerlord.Harmony</Id>
        <IsSelected>true</IsSelected>
      </UserModData>
      <UserModData>
        <Id>BetterExceptionWindow</Id>
        <IsSelected>true</IsSelected>
      </UserModData>
      <UserModData>
        <Id>Bannerlord.ButterLib</Id>
        <IsSelected>true</IsSelected>
      </UserModData>
      <UserModData>
        <Id>Bannerlord.UIExtenderEx</Id>
        <IsSelected>true</IsSelected>
      </UserModData>
      <UserModData>
        <Id>Bannerlord.MBOptionScreen</Id>
        <IsSelected>true</IsSelected>
      </UserModData>
      <UserModData>
        <Id>Native</Id>
        <IsSelected>true</IsSelected>
      </UserModData>
      <UserModData>
        <Id>SandBoxCore</Id>
        <IsSelected>true</IsSelected>
      </UserModData>
      <UserModData>
        <Id>Sandbox</Id>
        <IsSelected>true</IsSelected>
      </UserModData>
      <UserModData>
        <Id>StoryMode</Id>
        <IsSelected>true</IsSelected>
      </UserModData>
      <UserModData>
        <Id>CustomBattle</Id>
        <IsSelected>true</IsSelected>
      </UserModData>
      <UserModData>
        <Id>BirthAndDeath</Id>
        <IsSelected>true</IsSelected>
      </UserModData>
      <UserModData>
        <Id>AdonnaysTroopChanger</Id>
        <IsSelected>true</IsSelected>
      </UserModData>
      <UserModData>
        <Id>NobleTitlesPlus</Id>
        <IsSelected>true</IsSelected>
      </UserModData>
      <UserModData>
        <Id>WarlordsBattlefield</Id>
        <IsSelected>true</IsSelected>
      </UserModData>
      <UserModData>
        <Id>T7TroopUnlocker</Id>
        <IsSelected>true</IsSelected>
      </UserModData>
      <UserModData>
        <Id>GT_CarbonBody</Id>
        <IsSelected>true</IsSelected>
      </UserModData>
      <UserModData>
        <Id>GT_CarbonBody_Races_Elf</Id>
        <IsSelected>true</IsSelected>
      </UserModData>
      <UserModData>
        <Id>GT_CarbonBody_Outfits</Id>
        <IsSelected>true</IsSelected>
      </UserModData>
      <UserModData>
        <Id>New Female Armor for GT_CarbonBody</Id>
        <IsSelected>true</IsSelected>
      </UserModData>
      <UserModData>
        <Id>thiccc_elven_waifus</Id>
        <IsSelected>true</IsSelected>
      </UserModData>
      <UserModData>
        <Id>kult_of_the_kallipygos_2</Id>
        <IsSelected>true</IsSelected>
      </UserModData>
      <UserModData>
        <Id>ChineseIntegrationPack</Id>
        <IsSelected>true</IsSelected>
      </UserModData>
      <UserModData>
        <Id>CharacterReload</Id>
        <IsSelected>true</IsSelected>
      </UserModData>
      <UserModData>
        <Id>ExpandCombatUI</Id>
        <IsSelected>true</IsSelected>
      </UserModData>
      <UserModData>
        <Id>AutoResolveRebalanced</Id>
        <IsSelected>true</IsSelected>
      </UserModData>
      <UserModData>
        <Id>SortedIncome</Id>
        <IsSelected>true</IsSelected>
      </UserModData>
      <UserModData>
        <Id>KaosesCommon</Id>
        <IsSelected>true</IsSelected>
      </UserModData>
      <UserModData>
        <Id>KaosesTweaks</Id>
        <IsSelected>true</IsSelected>
      </UserModData>
      <UserModData>
        <Id>Bannerlord.Diplomacy</Id>
        <IsSelected>true</IsSelected>
      </UserModData>
      <UserModData>
        <Id>AgricultureEstate</Id>
        <IsSelected>true</IsSelected>
      </UserModData>
      <UserModData>
        <Id>BannerColorPersistence</Id>
        <IsSelected>true</IsSelected>
      </UserModData>
      <UserModData>
        <Id>BannerEditor</Id>
        <IsSelected>true</IsSelected>
      </UserModData>
      <UserModData>
        <Id>sy.AdjustableBandits</Id>
        <IsSelected>true</IsSelected>
      </UserModData>
      <UserModData>
        <Id>ArenaOverhaul</Id>
        <IsSelected>true</IsSelected>
      </UserModData>
      <UserModData>
        <Id>LivingParents</Id>
        <IsSelected>true</IsSelected>
      </UserModData>
      <UserModData>
        <Id>playerclan</Id>
        <IsSelected>true</IsSelected>
      </UserModData>
      <UserModData>
        <Id>AllegianceOverhaul</Id>
        <IsSelected>true</IsSelected>
      </UserModData>
      <UserModData>
        <Id>UsefullCompanions</Id>
        <IsSelected>true</IsSelected>
      </UserModData>
      <UserModData>
        <Id>ButterAchievements</Id>
        <IsSelected>true</IsSelected>
      </UserModData>
      <UserModData>
        <Id>MoreHeroInteractions</Id>
        <IsSelected>true</IsSelected>
      </UserModData>
      <UserModData>
        <Id>XorberaxLegacy</Id>
        <IsSelected>true</IsSelected>
      </UserModData>
      <UserModData>
        <Id>AchievementUnblocker</Id>
        <IsSelected>true</IsSelected>
      </UserModData>
      <UserModData>
        <Id>TestOfShield</Id>
        <IsSelected>true</IsSelected>
      </UserModData>
      <UserModData>
        <Id>TakeBoth</Id>
        <IsSelected>true</IsSelected>
      </UserModData>
      <UserModData>
        <Id>EquipBestItem</Id>
        <IsSelected>true</IsSelected>
      </UserModData>
      <UserModData>
        <Id>BetterCombat</Id>
        <IsSelected>true</IsSelected>
      </UserModData>
      <UserModData>
        <Id>KnockEmDown</Id>
        <IsSelected>false</IsSelected>
      </UserModData>
      <UserModData>
        <Id>Cheats</Id>
        <IsSelected>false</IsSelected>
      </UserModData>
      <UserModData>
        <Id>Fourberie</Id>
        <IsSelected>true</IsSelected>
      </UserModData>
      <UserModData>
        <Id>MorePrisonerInteractions</Id>
        <IsSelected>true</IsSelected>
      </UserModData>
      <UserModData>
        <Id>RandomEvents</Id>
        <IsSelected>true</IsSelected>
      </UserModData>
      <UserModData>
        <Id>BreakAndEnter</Id>
        <IsSelected>true</IsSelected>
      </UserModData>
      <UserModData>
        <Id>RighteousExecutions</Id>
        <IsSelected>true</IsSelected>
      </UserModData>
      <UserModData>
        <Id>Telepathy</Id>
        <IsSelected>true</IsSelected>
      </UserModData>
      <UserModData>
        <Id>TodayWeFeast</Id>
        <IsSelected>true</IsSelected>
      </UserModData>
      <UserModData>
        <Id>KingdomDestruction</Id>
        <IsSelected>true</IsSelected>
      </UserModData>
      <UserModData>
        <Id>zhugeliannu</Id>
        <IsSelected>true</IsSelected>
      </UserModData>
      <UserModData>
        <Id>CA_BloodSmoke_Items</Id>
        <IsSelected>true</IsSelected>
      </UserModData>
      <UserModData>
        <Id>JoinHouses</Id>
        <IsSelected>true</IsSelected>
      </UserModData>
      <UserModData>
        <Id>NeatedsNPCsUpgradeEquipment</Id>
        <IsSelected>true</IsSelected>
      </UserModData>
      <UserModData>
        <Id>PartyAIOverhaulCommands</Id>
        <IsSelected>true</IsSelected>
      </UserModData>
      <UserModData>
        <Id>BattleMiniMap</Id>
        <IsSelected>true</IsSelected>
      </UserModData>
      <UserModData>
        <Id>SueMoreSpouses</Id>
        <IsSelected>true</IsSelected>
      </UserModData>
      <UserModData>
        <Id>SpecialLoot</Id>
        <IsSelected>false</IsSelected>
      </UserModData>
      <UserModData>
        <Id>MarryAnyone</Id>
        <IsSelected>true</IsSelected>
      </UserModData>
      <UserModData>
        <Id>WorkshopsCompleted</Id>
        <IsSelected>true</IsSelected>
      </UserModData>
      <UserModData>
        <Id>BetterHorses</Id>
        <IsSelected>true</IsSelected>
      </UserModData>
      <UserModData>
        <Id>DeclareWarTogether</Id>
        <IsSelected>true</IsSelected>
      </UserModData>
      <UserModData>
        <Id>Vexillum</Id>
        <IsSelected>true</IsSelected>
      </UserModData>
      <UserModData>
        <Id>BannerFix</Id>
        <IsSelected>true</IsSelected>
      </UserModData>
      <UserModData>
        <Id>RaiseYourBanner</Id>
        <IsSelected>true</IsSelected>
      </UserModData>
      <UserModData>
        <Id>RaiseYourTorch</Id>
        <IsSelected>true</IsSelected>
      </UserModData>
      <UserModData>
        <Id>zCulturedStartCitillara</Id>
        <IsSelected>true</IsSelected>
      </UserModData>
      <UserModData>
        <Id>Bannerlord.CCsBanners</Id>
        <IsSelected>true</IsSelected>
      </UserModData>
      <UserModData>
        <Id>HideoutPlus</Id>
        <IsSelected>true</IsSelected>
      </UserModData>
      <UserModData>
        <Id>RTSCamera</Id>
        <IsSelected>true</IsSelected>
      </UserModData>
      <UserModData>
        <Id>RandomBodies</Id>
        <IsSelected>true</IsSelected>
      </UserModData>
      <UserModData>
        <Id>KingdomPoliticsExpanded</Id>
        <IsSelected>true</IsSelected>
      </UserModData>
      <UserModData>
        <Id>ArtOfWar</Id>
        <IsSelected>true</IsSelected>
      </UserModData>
      <UserModData>
        <Id>Artems Animations</Id>
        <IsSelected>true</IsSelected>
      </UserModData>
      <UserModData>
        <Id>DefendYourself</Id>
        <IsSelected>true</IsSelected>
      </UserModData>
      <UserModData>
        <Id>SurrenderTweaks</Id>
        <IsSelected>true</IsSelected>
      </UserModData>
      <UserModData>
        <Id>mosin_nagant_m91</Id>
        <IsSelected>true</IsSelected>
      </UserModData>
      <UserModData>
        <Id>PerfectExecutioner</Id>
        <IsSelected>true</IsSelected>
      </UserModData>
      <UserModData>
        <Id>ImmersiveBattlefields</Id>
        <IsSelected>true</IsSelected>
      </UserModData>
      <UserModData>
        <Id>Aragas.CastleTownWithHorse</Id>
        <IsSelected>true</IsSelected>
      </UserModData>
      <UserModData>
        <Id>ServeAsSoldier</Id>
        <IsSelected>true</IsSelected>
      </UserModData>
      <UserModData>
        <Id>ServeAsSoldierFix</Id>
        <IsSelected>true</IsSelected>
      </UserModData>
      <UserModData>
        <Id>TroopSort</Id>
        <IsSelected>true</IsSelected>
      </UserModData>
      <UserModData>
        <Id>GovernorsHandleIssues</Id>
        <IsSelected>true</IsSelected>
      </UserModData>
      <UserModData>
        <Id>BabyGrowthMod</Id>
        <IsSelected>true</IsSelected>
      </UserModData>
      <UserModData>
        <Id>Elfskin</Id>
        <IsSelected>true</IsSelected>
      </UserModData>
      <UserModData>
        <Id>BannerLib</Id>
        <IsSelected>true</IsSelected>
      </UserModData>
      <UserModData>
        <Id>MixMashChineseFantasyArmorPack</Id>
        <IsSelected>true</IsSelected>
      </UserModData>
      <UserModData>
        <Id>Mix Army</Id>
        <IsSelected>true</IsSelected>
      </UserModData>
      <UserModData>
        <Id>Mix Unlock</Id>
        <IsSelected>true</IsSelected>
      </UserModData>
      <UserModData>
        <Id>MolochsDuels</Id>
        <IsSelected>true</IsSelected>
      </UserModData>
      <UserModData>
        <Id>PlayerSwitcher</Id>
        <IsSelected>false</IsSelected>
      </UserModData>
      <UserModData>
        <Id>RenameAnySettlement</Id>
        <IsSelected>false</IsSelected>
      </UserModData>
      <UserModData>
        <Id>RevisitedCastles</Id>
        <IsSelected>true</IsSelected>
      </UserModData>
      <UserModData>
        <Id>TournamentOfChampions</Id>
        <IsSelected>true</IsSelected>
      </UserModData>
      <UserModData>
        <Id>Separatism</Id>
        <IsSelected>true</IsSelected>
      </UserModData>
      <UserModData>
        <Id>NoMarriageOffersForFemaleMembers</Id>
        <IsSelected>true</IsSelected>
      </UserModData>
      <UserModData>
        <Id>LongerCraftingParts</Id>
        <IsSelected>true</IsSelected>
      </UserModData>
      <UserModData>
        <Id>Heal on Kill</Id>
        <IsSelected>true</IsSelected>
      </UserModData>
      <UserModData>
        <Id>RelentlessSmith</Id>
        <IsSelected>true</IsSelected>
      </UserModData>
      <UserModData>
        <Id>Mix and match weapon pack</Id>
        <IsSelected>true</IsSelected>
      </UserModData>
      <UserModData>
        <Id>NoSafeModePrompt</Id>
        <IsSelected>true</IsSelected>
      </UserModData>
      <UserModData>
        <Id>zzy.ExtraLevelUp</Id>
        <IsSelected>true</IsSelected>
      </UserModData>
      <UserModData>
        <Id>HeroEnhancement</Id>
        <IsSelected>true</IsSelected>
      </UserModData>
      <UserModData>
        <Id>ArenaPack</Id>
        <IsSelected>true</IsSelected>
      </UserModData>
      <UserModData>
        <Id>UpgradeUrEquipment</Id>
        <IsSelected>true</IsSelected>
      </UserModData>
      <UserModData>
        <Id>sy.AdjustableLeveling</Id>
        <IsSelected>true</IsSelected>
      </UserModData>
      <UserModData>
        <Id>RTSCamera.CommandSystem</Id>
        <IsSelected>true</IsSelected>
      </UserModData>
      <UserModData>
        <Id>ScatterAroundExpanded</Id>
        <IsSelected>true</IsSelected>
      </UserModData>
      <UserModData>
        <Id>ArmyArrowCounter</Id>
        <IsSelected>false</IsSelected>
      </UserModData>
      <UserModData>
        <Id>CharacterManager</Id>
        <IsSelected>true</IsSelected>
      </UserModData>
      <UserModData>
        <Id>Bannerlord.MoreTraitInfo</Id>
        <IsSelected>true</IsSelected>
      </UserModData>
      <UserModData>
        <Id>WarAndAiTweaks</Id>
        <IsSelected>false</IsSelected>
      </UserModData>
      <UserModData>
        <Id>Bannerlord.EncyclopediaExtender</Id>
        <IsSelected>false</IsSelected>
      </UserModData>
      <UserModData>
        <Id>Bannerlord.FamilyTree</Id>
        <IsSelected>false</IsSelected>
      </UserModData>
      <UserModData>
        <Id>ImprovedGarrisons</Id>
        <IsSelected>false</IsSelected>
      </UserModData>
      <UserModData>
        <Id>WeaponGapFix</Id>
        <IsSelected>false</IsSelected>
      </UserModData>
      <UserModData>
        <Id>MyLittleWarband</Id>
        <IsSelected>false</IsSelected>
      </UserModData>
      <UserModData>
        <Id>Baijin Troops</Id>
        <IsSelected>false</IsSelected>
      </UserModData>
      <UserModData>
        <Id>DestroyKingdom</Id>
        <IsSelected>false</IsSelected>
      </UserModData>
      <UserModData>
        <Id>ChooseYourTroops</Id>
        <IsSelected>false</IsSelected>
      </UserModData>
      <UserModData>
        <Id>Bodyguards</Id>
        <IsSelected>false</IsSelected>
      </UserModData>
      <UserModData>
        <Id>Homesteads</Id>
        <IsSelected>true</IsSelected>
      </UserModData>
      <UserModData>
        <Id>CommandFactionParties</Id>
        <IsSelected>true</IsSelected>
      </UserModData>
      <UserModData>
        <Id>PlayerExecuteEdit</Id>
        <IsSelected>true</IsSelected>
      </UserModData>
      <UserModData>
        <Id>AIExecutioner</Id>
        <IsSelected>true</IsSelected>
      </UserModData>
      <UserModData>
        <Id>AIValuesLife</Id>
        <IsSelected>true</IsSelected>
      </UserModData>
      <UserModData>
        <Id>WealthyWorkshops</Id>
        <IsSelected>true</IsSelected>
      </UserModData>
      <UserModData>
        <Id>OpposeClan</Id>
        <IsSelected>true</IsSelected>
      </UserModData>
      <UserModData>
        <Id>LT_Nemesis</Id>
        <IsSelected>true</IsSelected>
      </UserModData>
      <UserModData>
        <Id>FixMOD_majimie</Id>
        <IsSelected>true</IsSelected>
      </UserModData>
      <UserModData>
        <Id>BetterTroopHUD</Id>
        <IsSelected>true</IsSelected>
      </UserModData>
      <UserModData>
        <Id>Bannerlord.EncyclopediaFilters</Id>
        <IsSelected>true</IsSelected>
      </UserModData>
      <UserModData>
        <Id>DrasticBattle</Id>
        <IsSelected>false</IsSelected>
      </UserModData>
      <UserModData>
        <Id>AllOneGender</Id>
        <IsSelected>false</IsSelected>
      </UserModData>
      <UserModData>
        <Id>Bannerlord.AssassinationMod</Id>
        <IsSelected>false</IsSelected>
      </UserModData>
      <UserModData>
        <Id>HoldCourt</Id>
        <IsSelected>false</IsSelected>
      </UserModData>
      <UserModData>
        <Id>CinematicCombat</Id>
        <IsSelected>false</IsSelected>
      </UserModData>
      <UserModData>
        <Id>ArmsDealer</Id>
        <IsSelected>false</IsSelected>
      </UserModData>
      <UserModData>
        <Id>ExpandKillLoot</Id>
        <IsSelected>true</IsSelected>
      </UserModData>
      <UserModData>
        <Id>MarryAnyoneUpdated</Id>
        <IsSelected>true</IsSelected>
      </UserModData>
    </ModDatas>
  </SingleplayerData>
  <MultiplayerData>
    <ModDatas>
      <UserModData>
        <Id>Native</Id>
        <IsSelected>true</IsSelected>
      </UserModData>
      <UserModData>
        <Id>Multiplayer</Id>
        <IsSelected>true</IsSelected>
      </UserModData>
      <UserModData>
        <Id>DedicatedCustomServerHelper</Id>
        <IsSelected>true</IsSelected>
      </UserModData>
    </ModDatas>
  </MultiplayerData>
  <DLLCheckData>
    <DLLData>
      <DLLCheckData>
        <DLLName>AgricultureEstate.dll</DLLName>
        <DLLVerifyInformation />
        <LatestSizeInBytes>0</LatestSizeInBytes>
        <IsDangerous>true</IsDangerous>
      </DLLCheckData>
      <DLLCheckData>
        <DLLName>AutoEquipCompanions.dll</DLLName>
        <DLLVerifyInformation />
        <LatestSizeInBytes>0</LatestSizeInBytes>
        <IsDangerous>true</IsDangerous>
      </DLLCheckData>
      <DLLCheckData>
        <DLLName>BannerColorPersistence.dll</DLLName>
        <DLLVerifyInformation />
        <LatestSizeInBytes>0</LatestSizeInBytes>
        <IsDangerous>true</IsDangerous>
      </DLLCheckData>
      <DLLCheckData>
        <DLLName>BetterCombat.dll</DLLName>
        <DLLVerifyInformation />
        <LatestSizeInBytes>0</LatestSizeInBytes>
        <IsDangerous>true</IsDangerous>
      </DLLCheckData>
      <DLLCheckData>
        <DLLName>BetterHUD.dll</DLLName>
        <DLLVerifyInformation />
        <LatestSizeInBytes>0</LatestSizeInBytes>
        <IsDangerous>true</IsDangerous>
      </DLLCheckData>
      <DLLCheckData>
        <DLLName>CharacterReload.dll</DLLName>
        <DLLVerifyInformation />
        <LatestSizeInBytes>0</LatestSizeInBytes>
        <IsDangerous>true</IsDangerous>
      </DLLCheckData>
      <DLLCheckData>
        <DLLName>DrasticBattle.dll</DLLName>
        <DLLVerifyInformation />
        <LatestSizeInBytes>0</LatestSizeInBytes>
        <IsDangerous>true</IsDangerous>
      </DLLCheckData>
      <DLLCheckData>
        <DLLName>HideoutPlus.dll</DLLName>
        <DLLVerifyInformation />
        <LatestSizeInBytes>0</LatestSizeInBytes>
        <IsDangerous>true</IsDangerous>
      </DLLCheckData>
      <DLLCheckData>
        <DLLName>ImprovedGarrisons.dll</DLLName>
        <DLLVerifyInformation />
        <LatestSizeInBytes>0</LatestSizeInBytes>
        <IsDangerous>true</IsDangerous>
      </DLLCheckData>
      <DLLCheckData>
        <DLLName>MyLittleWarband.dll</DLLName>
        <DLLVerifyInformation />
        <LatestSizeInBytes>0</LatestSizeInBytes>
        <IsDangerous>true</IsDangerous>
      </DLLCheckData>
      <DLLCheckData>
        <DLLName>OnGovernorChangedWorkAround.dll</DLLName>
        <DLLVerifyInformation />
        <LatestSizeInBytes>0</LatestSizeInBytes>
        <IsDangerous>true</IsDangerous>
      </DLLCheckData>
      <DLLCheckData>
        <DLLName>SueMoreSpouses.dll</DLLName>
        <DLLVerifyInformation />
        <LatestSizeInBytes>0</LatestSizeInBytes>
        <IsDangerous>true</IsDangerous>
      </DLLCheckData>
      <DLLCheckData>
        <DLLName>SueLordFromFamily.dll</DLLName>
        <DLLVerifyInformation />
        <LatestSizeInBytes>0</LatestSizeInBytes>
        <IsDangerous>true</IsDangerous>
      </DLLCheckData>
      <DLLCheckData>
        <DLLName>SueTheGeneration.dll</DLLName>
        <DLLVerifyInformation />
        <LatestSizeInBytes>0</LatestSizeInBytes>
        <IsDangerous>true</IsDangerous>
      </DLLCheckData>
      <DLLCheckData>
        <DLLName>SueMBService.dll</DLLName>
        <DLLVerifyInformation />
        <LatestSizeInBytes>0</LatestSizeInBytes>
        <IsDangerous>true</IsDangerous>
      </DLLCheckData>
      <DLLCheckData>
        <DLLName>T7TroopUnlocker.dll</DLLName>
        <DLLVerifyInformation />
        <LatestSizeInBytes>0</LatestSizeInBytes>
        <IsDangerous>true</IsDangerous>
      </DLLCheckData>
      <DLLCheckData>
        <DLLName>TrueBattleLoot.dll</DLLName>
        <DLLVerifyInformation />
        <LatestSizeInBytes>0</LatestSizeInBytes>
        <IsDangerous>true</IsDangerous>
      </DLLCheckData>
      <DLLCheckData>
        <DLLName>zCulturedStart.dll</DLLName>
        <DLLVerifyInformation />
        <LatestSizeInBytes>0</LatestSizeInBytes>
        <IsDangerous>true</IsDangerous>
      </DLLCheckData>
      <DLLCheckData>
        <DLLName>Bannerlord.Harmony.dll</DLLName>
        <DLLVerifyInformation />
        <LatestSizeInBytes>0</LatestSizeInBytes>
        <IsDangerous>true</IsDangerous>
      </DLLCheckData>
      <DLLCheckData>
        <DLLName>Bannerlord.UIExtenderEx.dll</DLLName>
        <DLLVerifyInformation />
        <LatestSizeInBytes>0</LatestSizeInBytes>
        <IsDangerous>true</IsDangerous>
      </DLLCheckData>
      <DLLCheckData>
        <DLLName>Bannerlord.ButterLib.dll</DLLName>
        <DLLVerifyInformation />
        <LatestSizeInBytes>0</LatestSizeInBytes>
        <IsDangerous>true</IsDangerous>
      </DLLCheckData>
      <DLLCheckData>
        <DLLName>MCMv4.dll</DLLName>
        <DLLVerifyInformation />
        <LatestSizeInBytes>0</LatestSizeInBytes>
        <IsDangerous>true</IsDangerous>
      </DLLCheckData>
      <DLLCheckData>
        <DLLName>MCMv4.UI.dll</DLLName>
        <DLLVerifyInformation />
        <LatestSizeInBytes>0</LatestSizeInBytes>
        <IsDangerous>true</IsDangerous>
      </DLLCheckData>
      <DLLCheckData>
        <DLLName>ModLib.dll</DLLName>
        <DLLVerifyInformation />
        <LatestSizeInBytes>0</LatestSizeInBytes>
        <IsDangerous>true</IsDangerous>
      </DLLCheckData>
      <DLLCheckData>
        <DLLName>ModLib.Definitions.dll</DLLName>
        <DLLVerifyInformation />
        <LatestSizeInBytes>0</LatestSizeInBytes>
        <IsDangerous>true</IsDangerous>
      </DLLCheckData>
      <DLLCheckData>
        <DLLName>MCMv4.Adapter.ModLib.dll</DLLName>
        <DLLVerifyInformation />
        <LatestSizeInBytes>0</LatestSizeInBytes>
        <IsDangerous>true</IsDangerous>
      </DLLCheckData>
      <DLLCheckData>
        <DLLName>RTSCamera.dll</DLLName>
        <DLLVerifyInformation />
        <LatestSizeInBytes>0</LatestSizeInBytes>
        <IsDangerous>true</IsDangerous>
      </DLLCheckData>
      <DLLCheckData>
        <DLLName>TroopSort.dll</DLLName>
        <DLLVerifyInformation />
        <LatestSizeInBytes>0</LatestSizeInBytes>
        <IsDangerous>true</IsDangerous>
      </DLLCheckData>
      <DLLCheckData>
        <DLLName>XorberaxLegacy.dll</DLLName>
        <DLLVerifyInformation />
        <LatestSizeInBytes>0</LatestSizeInBytes>
        <IsDangerous>true</IsDangerous>
      </DLLCheckData>
      <DLLCheckData>
        <DLLName>EncyclopediaExtender.dll</DLLName>
        <DLLVerifyInformation />
        <LatestSizeInBytes>0</LatestSizeInBytes>
        <IsDangerous>true</IsDangerous>
      </DLLCheckData>
      <DLLCheckData>
        <DLLName>LordsHaveMedicineSkill.dll</DLLName>
        <DLLVerifyInformation />
        <LatestSizeInBytes>0</LatestSizeInBytes>
        <IsDangerous>true</IsDangerous>
      </DLLCheckData>
      <DLLCheckData>
        <DLLName>BetterExceptionWindow.dll</DLLName>
        <DLLVerifyInformation />
        <LatestSizeInBytes>0</LatestSizeInBytes>
        <IsDangerous>true</IsDangerous>
      </DLLCheckData>
      <DLLCheckData>
        <DLLName>Fourberie.dll</DLLName>
        <DLLVerifyInformation />
        <LatestSizeInBytes>0</LatestSizeInBytes>
        <IsDangerous>true</IsDangerous>
      </DLLCheckData>
      <DLLCheckData>
        <DLLName>FamilyTree.dll</DLLName>
        <DLLVerifyInformation />
        <LatestSizeInBytes>0</LatestSizeInBytes>
        <IsDangerous>true</IsDangerous>
      </DLLCheckData>
      <DLLCheckData>
        <DLLName>ArmsDealer.dll</DLLName>
        <DLLVerifyInformation />
        <LatestSizeInBytes>0</LatestSizeInBytes>
        <IsDangerous>true</IsDangerous>
      </DLLCheckData>
      <DLLCheckData>
        <DLLName>BattleMiniMap.dll</DLLName>
        <DLLVerifyInformation />
        <LatestSizeInBytes>0</LatestSizeInBytes>
        <IsDangerous>true</IsDangerous>
      </DLLCheckData>
      <DLLCheckData>
        <DLLName>OverBurdingPartyWorkaround.dll</DLLName>
        <DLLVerifyInformation />
        <LatestSizeInBytes>0</LatestSizeInBytes>
        <IsDangerous>true</IsDangerous>
      </DLLCheckData>
      <DLLCheckData>
        <DLLName>AdonnaysTroopChanger.dll</DLLName>
        <DLLVerifyInformation />
        <LatestSizeInBytes>0</LatestSizeInBytes>
        <IsDangerous>true</IsDangerous>
      </DLLCheckData>
      <DLLCheckData>
        <DLLName>SaSFix.dll</DLLName>
        <DLLVerifyInformation />
        <LatestSizeInBytes>0</LatestSizeInBytes>
        <IsDangerous>true</IsDangerous>
      </DLLCheckData>
      <DLLCheckData>
        <DLLName>ServeAsSoldier.dll</DLLName>
        <DLLVerifyInformation />
        <LatestSizeInBytes>0</LatestSizeInBytes>
        <IsDangerous>true</IsDangerous>
      </DLLCheckData>
      <DLLCheckData>
        <DLLName>ArrowCam.dll</DLLName>
        <DLLVerifyInformation />
        <LatestSizeInBytes>0</LatestSizeInBytes>
        <IsDangerous>true</IsDangerous>
      </DLLCheckData>
      <DLLCheckData>
        <DLLName>ScatterAroundExpanded.dll</DLLName>
        <DLLVerifyInformation />
        <LatestSizeInBytes>0</LatestSizeInBytes>
        <IsDangerous>true</IsDangerous>
      </DLLCheckData>
      <DLLCheckData>
        <DLLName>CharacterManager.dll</DLLName>
        <DLLVerifyInformation />
        <LatestSizeInBytes>0</LatestSizeInBytes>
        <IsDangerous>true</IsDangerous>
      </DLLCheckData>
      <DLLCheckData>
        <DLLName>RTSCamera.CommandSystem.dll</DLLName>
        <DLLVerifyInformation />
        <LatestSizeInBytes>0</LatestSizeInBytes>
        <IsDangerous>true</IsDangerous>
      </DLLCheckData>
      <DLLCheckData>
        <DLLName>MCMv5.dll</DLLName>
        <DLLVerifyInformation />
        <LatestSizeInBytes>0</LatestSizeInBytes>
        <IsDangerous>true</IsDangerous>
      </DLLCheckData>
      <DLLCheckData>
        <DLLName>MCMv5.UI.dll</DLLName>
        <DLLVerifyInformation />
        <LatestSizeInBytes>0</LatestSizeInBytes>
        <IsDangerous>true</IsDangerous>
      </DLLCheckData>
      <DLLCheckData>
        <DLLName>EnableAchievement.dll</DLLName>
        <DLLVerifyInformation />
        <LatestSizeInBytes>0</LatestSizeInBytes>
        <IsDangerous>true</IsDangerous>
      </DLLCheckData>
      <DLLCheckData>
        <DLLName>BannerlordCheats.dll</DLLName>
        <DLLVerifyInformation />
        <LatestSizeInBytes>0</LatestSizeInBytes>
        <IsDangerous>true</IsDangerous>
      </DLLCheckData>
      <DLLCheckData>
        <DLLName>WorkshopsAdvanced.dll</DLLName>
        <DLLVerifyInformation />
        <LatestSizeInBytes>0</LatestSizeInBytes>
        <IsDangerous>true</IsDangerous>
      </DLLCheckData>
      <DLLCheckData>
        <DLLName>Bannerlord.Diplomacy.1.0.0.dll</DLLName>
        <DLLVerifyInformation />
        <LatestSizeInBytes>0</LatestSizeInBytes>
        <IsDangerous>true</IsDangerous>
      </DLLCheckData>
      <DLLCheckData>
        <DLLName>PartyScreenEnhancements.dll</DLLName>
        <DLLVerifyInformation />
        <LatestSizeInBytes>0</LatestSizeInBytes>
        <IsDangerous>true</IsDangerous>
      </DLLCheckData>
      <DLLCheckData>
        <DLLName>AutoResolveRebalanced.dll</DLLName>
        <DLLVerifyInformation />
        <LatestSizeInBytes>0</LatestSizeInBytes>
        <IsDangerous>true</IsDangerous>
      </DLLCheckData>
      <DLLCheckData>
        <DLLName>PowerfulHeroes.dll</DLLName>
        <DLLVerifyInformation />
        <LatestSizeInBytes>0</LatestSizeInBytes>
        <IsDangerous>true</IsDangerous>
      </DLLCheckData>
      <DLLCheckData>
        <DLLName>RelentlessSmith.dll</DLLName>
        <DLLVerifyInformation />
        <LatestSizeInBytes>0</LatestSizeInBytes>
        <IsDangerous>true</IsDangerous>
      </DLLCheckData>
      <DLLCheckData>
        <DLLName>EquipBestItem.dll</DLLName>
        <DLLVerifyInformation />
        <LatestSizeInBytes>0</LatestSizeInBytes>
        <IsDangerous>true</IsDangerous>
      </DLLCheckData>
      <DLLCheckData>
        <DLLName>Bannerlord.ModuleLoader.Bannerlord.Diplomacy.dll</DLLName>
        <DLLVerifyInformation />
        <LatestSizeInBytes>0</LatestSizeInBytes>
        <IsDangerous>true</IsDangerous>
      </DLLCheckData>
      <DLLCheckData>
        <DLLName>MixAndMatchWeaponPack.dll</DLLName>
        <DLLVerifyInformation />
        <LatestSizeInBytes>0</LatestSizeInBytes>
        <IsDangerous>true</IsDangerous>
      </DLLCheckData>
      <DLLCheckData>
        <DLLName>FamilyControl.dll</DLLName>
        <DLLVerifyInformation />
        <LatestSizeInBytes>0</LatestSizeInBytes>
        <IsDangerous>true</IsDangerous>
      </DLLCheckData>
      <DLLCheckData>
        <DLLName>MaxAttribute.dll</DLLName>
        <DLLVerifyInformation />
        <LatestSizeInBytes>0</LatestSizeInBytes>
        <IsDangerous>true</IsDangerous>
      </DLLCheckData>
      <DLLCheckData>
        <DLLName>JoinHouses.dll</DLLName>
        <DLLVerifyInformation />
        <LatestSizeInBytes>0</LatestSizeInBytes>
        <IsDangerous>true</IsDangerous>
      </DLLCheckData>
      <DLLCheckData>
        <DLLName>UnlimitedMaxAttribute.dll</DLLName>
        <DLLVerifyInformation />
        <LatestSizeInBytes>0</LatestSizeInBytes>
        <IsDangerous>true</IsDangerous>
      </DLLCheckData>
      <DLLCheckData>
        <DLLName>zzy.ExtraLevelUp.dll</DLLName>
        <DLLVerifyInformation />
        <LatestSizeInBytes>0</LatestSizeInBytes>
        <IsDangerous>true</IsDangerous>
      </DLLCheckData>
      <DLLCheckData>
        <DLLName>SortedIncome.dll</DLLName>
        <DLLVerifyInformation />
        <LatestSizeInBytes>0</LatestSizeInBytes>
        <IsDangerous>true</IsDangerous>
      </DLLCheckData>
      <DLLCheckData>
        <DLLName>LongerCraftingParts.dll</DLLName>
        <DLLVerifyInformation />
        <LatestSizeInBytes>0</LatestSizeInBytes>
        <IsDangerous>true</IsDangerous>
      </DLLCheckData>
      <DLLCheckData>
        <DLLName>Immersive Sergeant.dll</DLLName>
        <DLLVerifyInformation />
        <LatestSizeInBytes>0</LatestSizeInBytes>
        <IsDangerous>true</IsDangerous>
      </DLLCheckData>
      <DLLCheckData>
        <DLLName>NoMarriageOffersForFemaleMembers.dll</DLLName>
        <DLLVerifyInformation />
        <LatestSizeInBytes>0</LatestSizeInBytes>
        <IsDangerous>true</IsDangerous>
      </DLLCheckData>
      <DLLCheckData>
        <DLLName>NobleTitles.dll</DLLName>
        <DLLVerifyInformation />
        <LatestSizeInBytes>0</LatestSizeInBytes>
        <IsDangerous>true</IsDangerous>
      </DLLCheckData>
      <DLLCheckData>
        <DLLName>PlayerSwitcher.dll</DLLName>
        <DLLVerifyInformation />
        <LatestSizeInBytes>0</LatestSizeInBytes>
        <IsDangerous>true</IsDangerous>
      </DLLCheckData>
      <DLLCheckData>
        <DLLName>Separatism.dll</DLLName>
        <DLLVerifyInformation />
        <LatestSizeInBytes>0</LatestSizeInBytes>
        <IsDangerous>true</IsDangerous>
      </DLLCheckData>
      <DLLCheckData>
        <DLLName>MyOwnTroops.dll</DLLName>
        <DLLVerifyInformation />
        <LatestSizeInBytes>0</LatestSizeInBytes>
        <IsDangerous>true</IsDangerous>
      </DLLCheckData>
      <DLLCheckData>
        <DLLName>KaosesTweaks.dll</DLLName>
        <DLLVerifyInformation />
        <LatestSizeInBytes>0</LatestSizeInBytes>
        <IsDangerous>true</IsDangerous>
      </DLLCheckData>
      <DLLCheckData>
        <DLLName>HealthOnKill.dll</DLLName>
        <DLLVerifyInformation />
        <LatestSizeInBytes>0</LatestSizeInBytes>
        <IsDangerous>true</IsDangerous>
      </DLLCheckData>
      <DLLCheckData>
        <DLLName>GapFix.dll</DLLName>
        <DLLVerifyInformation />
        <LatestSizeInBytes>0</LatestSizeInBytes>
        <IsDangerous>true</IsDangerous>
      </DLLCheckData>
      <DLLCheckData>
        <DLLName>T7TroopUnlockerHarmony.dll</DLLName>
        <DLLVerifyInformation />
        <LatestSizeInBytes>0</LatestSizeInBytes>
        <IsDangerous>true</IsDangerous>
      </DLLCheckData>
      <DLLCheckData>
        <DLLName>ChineseWarband.dll</DLLName>
        <DLLVerifyInformation />
        <LatestSizeInBytes>0</LatestSizeInBytes>
        <IsDangerous>true</IsDangerous>
      </DLLCheckData>
      <DLLCheckData>
        <DLLName>DeadShot.dll</DLLName>
        <DLLVerifyInformation />
        <LatestSizeInBytes>0</LatestSizeInBytes>
        <IsDangerous>true</IsDangerous>
      </DLLCheckData>
      <DLLCheckData>
        <DLLName>DestroyKingdom.1.0.0.dll</DLLName>
        <DLLVerifyInformation />
        <LatestSizeInBytes>0</LatestSizeInBytes>
        <IsDangerous>true</IsDangerous>
      </DLLCheckData>
      <DLLCheckData>
        <DLLName>EverYoung.dll</DLLName>
        <DLLVerifyInformation />
        <LatestSizeInBytes>0</LatestSizeInBytes>
        <IsDangerous>true</IsDangerous>
      </DLLCheckData>
      <DLLCheckData>
        <DLLName>MarryAnyone.dll</DLLName>
        <DLLVerifyInformation />
        <LatestSizeInBytes>0</LatestSizeInBytes>
        <IsDangerous>true</IsDangerous>
      </DLLCheckData>
      <DLLCheckData>
        <DLLName>HeroEnhancement.dll</DLLName>
        <DLLVerifyInformation />
        <LatestSizeInBytes>0</LatestSizeInBytes>
        <IsDangerous>true</IsDangerous>
      </DLLCheckData>
      <DLLCheckData>
        <DLLName>TrueRecruitmentCosts.dll</DLLName>
        <DLLVerifyInformation />
        <LatestSizeInBytes>0</LatestSizeInBytes>
        <IsDangerous>true</IsDangerous>
      </DLLCheckData>
      <DLLCheckData>
        <DLLName>MCM.UI.Adapter.MCMv5.dll</DLLName>
        <DLLVerifyInformation />
        <LatestSizeInBytes>0</LatestSizeInBytes>
        <IsDangerous>true</IsDangerous>
      </DLLCheckData>
      <DLLCheckData>
        <DLLName>Bannerlord.ModuleLoader.NobleTitles.dll</DLLName>
        <DLLVerifyInformation />
        <LatestSizeInBytes>0</LatestSizeInBytes>
        <IsDangerous>true</IsDangerous>
      </DLLCheckData>
      <DLLCheckData>
        <DLLName>BannerCraft.dll</DLLName>
        <DLLVerifyInformation />
        <LatestSizeInBytes>0</LatestSizeInBytes>
        <IsDangerous>true</IsDangerous>
      </DLLCheckData>
      <DLLCheckData>
        <DLLName>AdjustableBandits.dll</DLLName>
        <DLLVerifyInformation />
        <LatestSizeInBytes>0</LatestSizeInBytes>
        <IsDangerous>true</IsDangerous>
      </DLLCheckData>
      <DLLCheckData>
        <DLLName>BannerEditor.dll</DLLName>
        <DLLVerifyInformation />
        <LatestSizeInBytes>0</LatestSizeInBytes>
        <IsDangerous>true</IsDangerous>
      </DLLCheckData>
      <DLLCheckData>
        <DLLName>KingdomPoliticsExpanded.dll</DLLName>
        <DLLVerifyInformation />
        <LatestSizeInBytes>0</LatestSizeInBytes>
        <IsDangerous>true</IsDangerous>
      </DLLCheckData>
      <DLLCheckData>
        <DLLName>KnockEmDown.dll</DLLName>
        <DLLVerifyInformation />
        <LatestSizeInBytes>0</LatestSizeInBytes>
        <IsDangerous>true</IsDangerous>
      </DLLCheckData>
      <DLLCheckData>
        <DLLName>ROT.dll</DLLName>
        <DLLVerifyInformation />
        <LatestSizeInBytes>0</LatestSizeInBytes>
        <IsDangerous>true</IsDangerous>
      </DLLCheckData>
      <DLLCheckData>
        <DLLName>UniqueCompanions.dll</DLLName>
        <DLLVerifyInformation />
        <LatestSizeInBytes>0</LatestSizeInBytes>
        <IsDangerous>true</IsDangerous>
      </DLLCheckData>
      <DLLCheckData>
        <DLLName>BanditLeaders.dll</DLLName>
        <DLLVerifyInformation />
        <LatestSizeInBytes>0</LatestSizeInBytes>
        <IsDangerous>true</IsDangerous>
      </DLLCheckData>
      <DLLCheckData>
        <DLLName>KingdomDestruction.dll</DLLName>
        <DLLVerifyInformation />
        <LatestSizeInBytes>0</LatestSizeInBytes>
        <IsDangerous>true</IsDangerous>
      </DLLCheckData>
      <DLLCheckData>
        <DLLName>GankM.dll</DLLName>
        <DLLVerifyInformation />
        <LatestSizeInBytes>0</LatestSizeInBytes>
        <IsDangerous>true</IsDangerous>
      </DLLCheckData>
      <DLLCheckData>
        <DLLName>BanditsLeaveHideouts.dll</DLLName>
        <DLLVerifyInformation />
        <LatestSizeInBytes>0</LatestSizeInBytes>
        <IsDangerous>true</IsDangerous>
      </DLLCheckData>
      <DLLCheckData>
        <DLLName>CustomWarMechanics.dll</DLLName>
        <DLLVerifyInformation />
        <LatestSizeInBytes>0</LatestSizeInBytes>
        <IsDangerous>true</IsDangerous>
      </DLLCheckData>
      <DLLCheckData>
        <DLLName>StartDatePrototype.dll</DLLName>
        <DLLVerifyInformation />
        <LatestSizeInBytes>0</LatestSizeInBytes>
        <IsDangerous>true</IsDangerous>
      </DLLCheckData>
      <DLLCheckData>
        <DLLName>TradeBoundFix.dll</DLLName>
        <DLLVerifyInformation />
        <LatestSizeInBytes>0</LatestSizeInBytes>
        <IsDangerous>true</IsDangerous>
      </DLLCheckData>
      <DLLCheckData>
        <DLLName>SettlementDistanceCache.dll</DLLName>
        <DLLVerifyInformation />
        <LatestSizeInBytes>0</LatestSizeInBytes>
        <IsDangerous>true</IsDangerous>
      </DLLCheckData>
      <DLLCheckData>
        <DLLName>Aurelian.MapFix.dll</DLLName>
        <DLLVerifyInformation />
        <LatestSizeInBytes>0</LatestSizeInBytes>
        <IsDangerous>true</IsDangerous>
      </DLLCheckData>
      <DLLCheckData>
        <DLLName>KaosesCommon.dll</DLLName>
        <DLLVerifyInformation />
        <LatestSizeInBytes>0</LatestSizeInBytes>
        <IsDangerous>true</IsDangerous>
      </DLLCheckData>
      <DLLCheckData>
        <DLLName>Bannerlord.ModuleLoader.ArenaOverhaul.dll</DLLName>
        <DLLVerifyInformation />
        <LatestSizeInBytes>0</LatestSizeInBytes>
        <IsDangerous>true</IsDangerous>
      </DLLCheckData>
      <DLLCheckData>
        <DLLName>AgeSettings.dll</DLLName>
        <DLLVerifyInformation />
        <LatestSizeInBytes>0</LatestSizeInBytes>
        <IsDangerous>true</IsDangerous>
      </DLLCheckData>
      <DLLCheckData>
        <DLLName>Bodyguards.dll</DLLName>
        <DLLVerifyInformation />
        <LatestSizeInBytes>0</LatestSizeInBytes>
        <IsDangerous>true</IsDangerous>
      </DLLCheckData>
      <DLLCheckData>
        <DLLName>Telepathy.dll</DLLName>
        <DLLVerifyInformation />
        <LatestSizeInBytes>0</LatestSizeInBytes>
        <IsDangerous>true</IsDangerous>
      </DLLCheckData>
      <DLLCheckData>
        <DLLName>TakeBoth.dll</DLLName>
        <DLLVerifyInformation />
        <LatestSizeInBytes>0</LatestSizeInBytes>
        <IsDangerous>true</IsDangerous>
      </DLLCheckData>
      <DLLCheckData>
        <DLLName>Bannerlord.ModuleLoader.AllegianceOverhaul.dll</DLLName>
        <DLLVerifyInformation />
        <LatestSizeInBytes>0</LatestSizeInBytes>
        <IsDangerous>true</IsDangerous>
      </DLLCheckData>
      <DLLCheckData>
        <DLLName>PartyAIOverhaulAndCommands.dll</DLLName>
        <DLLVerifyInformation />
        <LatestSizeInBytes>0</LatestSizeInBytes>
        <IsDangerous>true</IsDangerous>
      </DLLCheckData>
      <DLLCheckData>
        <DLLName>UsefulCompanions.dll</DLLName>
        <DLLVerifyInformation />
        <LatestSizeInBytes>0</LatestSizeInBytes>
        <IsDangerous>true</IsDangerous>
      </DLLCheckData>
      <DLLCheckData>
        <DLLName>ButterAchievements.dll</DLLName>
        <DLLVerifyInformation />
        <LatestSizeInBytes>0</LatestSizeInBytes>
        <IsDangerous>true</IsDangerous>
      </DLLCheckData>
      <DLLCheckData>
        <DLLName>MoreHeroInteractions.dll</DLLName>
        <DLLVerifyInformation />
        <LatestSizeInBytes>0</LatestSizeInBytes>
        <IsDangerous>true</IsDangerous>
      </DLLCheckData>
      <DLLCheckData>
        <DLLName>AchievementUnblocker.dll</DLLName>
        <DLLVerifyInformation />
        <LatestSizeInBytes>0</LatestSizeInBytes>
        <IsDangerous>true</IsDangerous>
      </DLLCheckData>
      <DLLCheckData>
        <DLLName>TestOfShield.dll</DLLName>
        <DLLVerifyInformation />
        <LatestSizeInBytes>0</LatestSizeInBytes>
        <IsDangerous>true</IsDangerous>
      </DLLCheckData>
      <DLLCheckData>
        <DLLName>MorePrisonerInteractions.dll</DLLName>
        <DLLVerifyInformation />
        <LatestSizeInBytes>0</LatestSizeInBytes>
        <IsDangerous>true</IsDangerous>
      </DLLCheckData>
      <DLLCheckData>
        <DLLName>RandomEvents.dll</DLLName>
        <DLLVerifyInformation />
        <LatestSizeInBytes>0</LatestSizeInBytes>
        <IsDangerous>true</IsDangerous>
      </DLLCheckData>
      <DLLCheckData>
        <DLLName>BreakAndEnter.dll</DLLName>
        <DLLVerifyInformation />
        <LatestSizeInBytes>0</LatestSizeInBytes>
        <IsDangerous>true</IsDangerous>
      </DLLCheckData>
      <DLLCheckData>
        <DLLName>RighteousExecutions.dll</DLLName>
        <DLLVerifyInformation />
        <LatestSizeInBytes>0</LatestSizeInBytes>
        <IsDangerous>true</IsDangerous>
      </DLLCheckData>
      <DLLCheckData>
        <DLLName>TodayWeFeast.dll</DLLName>
        <DLLVerifyInformation />
        <LatestSizeInBytes>0</LatestSizeInBytes>
        <IsDangerous>true</IsDangerous>
      </DLLCheckData>
      <DLLCheckData>
        <DLLName>NoSafeModePrompt.dll</DLLName>
        <DLLVerifyInformation />
        <LatestSizeInBytes>0</LatestSizeInBytes>
        <IsDangerous>true</IsDangerous>
      </DLLCheckData>
      <DLLCheckData>
        <DLLName>AdjustableLeveling.dll</DLLName>
        <DLLVerifyInformation />
        <LatestSizeInBytes>0</LatestSizeInBytes>
        <IsDangerous>true</IsDangerous>
      </DLLCheckData>
      <DLLCheckData>
        <DLLName>LT_Education.dll</DLLName>
        <DLLVerifyInformation />
        <LatestSizeInBytes>0</LatestSizeInBytes>
        <IsDangerous>true</IsDangerous>
      </DLLCheckData>
      <DLLCheckData>
        <DLLName>NeatedNPCsupgradeEquipment.dll</DLLName>
        <DLLVerifyInformation />
        <LatestSizeInBytes>0</LatestSizeInBytes>
        <IsDangerous>true</IsDangerous>
      </DLLCheckData>
      <DLLCheckData>
        <DLLName>Leveling_Rebalance.dll</DLLName>
        <DLLVerifyInformation />
        <LatestSizeInBytes>0</LatestSizeInBytes>
        <IsDangerous>true</IsDangerous>
      </DLLCheckData>
      <DLLCheckData>
        <DLLName>SpecialLoot.dll</DLLName>
        <DLLVerifyInformation />
        <LatestSizeInBytes>0</LatestSizeInBytes>
        <IsDangerous>true</IsDangerous>
      </DLLCheckData>
      <DLLCheckData>
        <DLLName>LogRaamBattleLoot.dll</DLLName>
        <DLLVerifyInformation />
        <LatestSizeInBytes>0</LatestSizeInBytes>
        <IsDangerous>true</IsDangerous>
      </DLLCheckData>
      <DLLCheckData>
        <DLLName>RealisticWeather.dll</DLLName>
        <DLLVerifyInformation />
        <LatestSizeInBytes>0</LatestSizeInBytes>
        <IsDangerous>true</IsDangerous>
      </DLLCheckData>
      <DLLCheckData>
        <DLLName>WorkshopsCompleted.dll</DLLName>
        <DLLVerifyInformation />
        <LatestSizeInBytes>0</LatestSizeInBytes>
        <IsDangerous>true</IsDangerous>
      </DLLCheckData>
      <DLLCheckData>
        <DLLName>BetterHorses.dll</DLLName>
        <DLLVerifyInformation />
        <LatestSizeInBytes>0</LatestSizeInBytes>
        <IsDangerous>true</IsDangerous>
      </DLLCheckData>
      <DLLCheckData>
        <DLLName>DeclareWarTogether.dll</DLLName>
        <DLLVerifyInformation />
        <LatestSizeInBytes>0</LatestSizeInBytes>
        <IsDangerous>true</IsDangerous>
      </DLLCheckData>
      <DLLCheckData>
        <DLLName>Bannerlord.ModuleLoader.Bannerlord.EncyclopediaExtender.dll</DLLName>
        <DLLVerifyInformation />
        <LatestSizeInBytes>0</LatestSizeInBytes>
        <IsDangerous>true</IsDangerous>
      </DLLCheckData>
      <DLLCheckData>
        <DLLName>Perfect Fire Arrows.dll</DLLName>
        <DLLVerifyInformation />
        <LatestSizeInBytes>0</LatestSizeInBytes>
        <IsDangerous>true</IsDangerous>
      </DLLCheckData>
      <DLLCheckData>
        <DLLName>Raise your Banner.dll</DLLName>
        <DLLVerifyInformation />
        <LatestSizeInBytes>0</LatestSizeInBytes>
        <IsDangerous>true</IsDangerous>
      </DLLCheckData>
      <DLLCheckData>
        <DLLName>Raise your Torch.dll</DLLName>
        <DLLVerifyInformation />
        <LatestSizeInBytes>0</LatestSizeInBytes>
        <IsDangerous>true</IsDangerous>
      </DLLCheckData>
      <DLLCheckData>
        <DLLName>UpgradeUrEquipment.dll</DLLName>
        <DLLVerifyInformation />
        <LatestSizeInBytes>0</LatestSizeInBytes>
        <IsDangerous>true</IsDangerous>
      </DLLCheckData>
      <DLLCheckData>
        <DLLName>ChooseYourTroops.dll</DLLName>
        <DLLVerifyInformation />
        <LatestSizeInBytes>0</LatestSizeInBytes>
        <IsDangerous>true</IsDangerous>
      </DLLCheckData>
      <DLLCheckData>
        <DLLName>Erraynhotcoffee.dll</DLLName>
        <DLLVerifyInformation />
        <LatestSizeInBytes>0</LatestSizeInBytes>
        <IsDangerous>true</IsDangerous>
      </DLLCheckData>
      <DLLCheckData>
        <DLLName>WalkersOfCalradia.dll</DLLName>
        <DLLVerifyInformation />
        <LatestSizeInBytes>0</LatestSizeInBytes>
        <IsDangerous>true</IsDangerous>
      </DLLCheckData>
      <DLLCheckData>
        <DLLName>LifeInCalradia_Housing.dll</DLLName>
        <DLLVerifyInformation />
        <LatestSizeInBytes>0</LatestSizeInBytes>
        <IsDangerous>true</IsDangerous>
      </DLLCheckData>
      <DLLCheckData>
        <DLLName>Bannerlord.ModuleLoader.Bannerlord.FamilyTree.dll</DLLName>
        <DLLVerifyInformation />
        <LatestSizeInBytes>0</LatestSizeInBytes>
        <IsDangerous>true</IsDangerous>
      </DLLCheckData>
      <DLLCheckData>
        <DLLName>CutThroughEveryone.dll</DLLName>
        <DLLVerifyInformation />
        <LatestSizeInBytes>0</LatestSizeInBytes>
        <IsDangerous>true</IsDangerous>
      </DLLCheckData>
      <DLLCheckData>
        <DLLName>Bannerlord.ModuleLoader.YouKeepWhatYouKill.dll</DLLName>
        <DLLVerifyInformation />
        <LatestSizeInBytes>0</LatestSizeInBytes>
        <IsDangerous>true</IsDangerous>
      </DLLCheckData>
      <DLLCheckData>
        <DLLName>ArtOfWar.dll</DLLName>
        <DLLVerifyInformation />
        <LatestSizeInBytes>0</LatestSizeInBytes>
        <IsDangerous>true</IsDangerous>
      </DLLCheckData>
      <DLLCheckData>
        <DLLName>WarAndAiTweaks.dll</DLLName>
        <DLLVerifyInformation />
        <LatestSizeInBytes>0</LatestSizeInBytes>
        <IsDangerous>true</IsDangerous>
      </DLLCheckData>
      <DLLCheckData>
        <DLLName>DefendYourself.dll</DLLName>
        <DLLVerifyInformation />
        <LatestSizeInBytes>0</LatestSizeInBytes>
        <IsDangerous>true</IsDangerous>
      </DLLCheckData>
      <DLLCheckData>
        <DLLName>SurrenderTweaks.dll</DLLName>
        <DLLVerifyInformation />
        <LatestSizeInBytes>0</LatestSizeInBytes>
        <IsDangerous>true</IsDangerous>
      </DLLCheckData>
      <DLLCheckData>
        <DLLName>AutoCrossbow.dll</DLLName>
        <DLLVerifyInformation />
        <LatestSizeInBytes>0</LatestSizeInBytes>
        <IsDangerous>true</IsDangerous>
      </DLLCheckData>
      <DLLCheckData>
        <DLLName>NobleTitlesPlus.dll</DLLName>
        <DLLVerifyInformation />
        <LatestSizeInBytes>0</LatestSizeInBytes>
        <IsDangerous>true</IsDangerous>
      </DLLCheckData>
      <DLLCheckData>
        <DLLName>BastardChildren.dll</DLLName>
        <DLLVerifyInformation />
        <LatestSizeInBytes>0</LatestSizeInBytes>
        <IsDangerous>true</IsDangerous>
      </DLLCheckData>
      <DLLCheckData>
        <DLLName>Concubines.dll</DLLName>
        <DLLVerifyInformation />
        <LatestSizeInBytes>0</LatestSizeInBytes>
        <IsDangerous>true</IsDangerous>
      </DLLCheckData>
      <DLLCheckData>
        <DLLName>DismembermentPlus.dll</DLLName>
        <DLLVerifyInformation />
        <LatestSizeInBytes>0</LatestSizeInBytes>
        <IsDangerous>true</IsDangerous>
      </DLLCheckData>
      <DLLCheckData>
        <DLLName>ServeAsSoldierFix.dll</DLLName>
        <DLLVerifyInformation />
        <LatestSizeInBytes>0</LatestSizeInBytes>
        <IsDangerous>true</IsDangerous>
      </DLLCheckData>
      <DLLCheckData>
        <DLLName>PerfectExecutioner.dll</DLLName>
        <DLLVerifyInformation />
        <LatestSizeInBytes>0</LatestSizeInBytes>
        <IsDangerous>true</IsDangerous>
      </DLLCheckData>
      <DLLCheckData>
        <DLLName>Immersive Battlefields.dll</DLLName>
        <DLLVerifyInformation />
        <LatestSizeInBytes>0</LatestSizeInBytes>
        <IsDangerous>true</IsDangerous>
      </DLLCheckData>
      <DLLCheckData>
        <DLLName>BetterSkills.dll</DLLName>
        <DLLVerifyInformation />
        <LatestSizeInBytes>0</LatestSizeInBytes>
        <IsDangerous>true</IsDangerous>
      </DLLCheckData>
      <DLLCheckData>
        <DLLName>Aragas.CastleTownWithHorse.dll</DLLName>
        <DLLVerifyInformation />
        <LatestSizeInBytes>0</LatestSizeInBytes>
        <IsDangerous>true</IsDangerous>
      </DLLCheckData>
      <DLLCheckData>
        <DLLName>GarrisonDoSomething.dll</DLLName>
        <DLLVerifyInformation />
        <LatestSizeInBytes>0</LatestSizeInBytes>
        <IsDangerous>true</IsDangerous>
      </DLLCheckData>
      <DLLCheckData>
        <DLLName>HotButterFix.dll</DLLName>
        <DLLVerifyInformation />
        <LatestSizeInBytes>0</LatestSizeInBytes>
        <IsDangerous>true</IsDangerous>
      </DLLCheckData>
      <DLLCheckData>
        <DLLName>RealisticBattleSounds.dll</DLLName>
        <DLLVerifyInformation />
        <LatestSizeInBytes>0</LatestSizeInBytes>
        <IsDangerous>true</IsDangerous>
      </DLLCheckData>
      <DLLCheckData>
        <DLLName>GovernorsHandleIssues.dll</DLLName>
        <DLLVerifyInformation />
        <LatestSizeInBytes>0</LatestSizeInBytes>
        <IsDangerous>true</IsDangerous>
      </DLLCheckData>
      <DLLCheckData>
        <DLLName>Bannerlord.ModuleLoader.Bannerlord.MoreTraitInfo.dll</DLLName>
        <DLLVerifyInformation />
        <LatestSizeInBytes>0</LatestSizeInBytes>
        <IsDangerous>true</IsDangerous>
      </DLLCheckData>
      <DLLCheckData>
        <DLLName>BabyGrowthMod.dll</DLLName>
        <DLLVerifyInformation />
        <LatestSizeInBytes>0</LatestSizeInBytes>
        <IsDangerous>true</IsDangerous>
      </DLLCheckData>
      <DLLCheckData>
        <DLLName>BannerLib.Input.dll</DLLName>
        <DLLVerifyInformation />
        <LatestSizeInBytes>0</LatestSizeInBytes>
        <IsDangerous>true</IsDangerous>
      </DLLCheckData>
      <DLLCheckData>
        <DLLName>HoldCourt.dll</DLLName>
        <DLLVerifyInformation />
        <LatestSizeInBytes>0</LatestSizeInBytes>
        <IsDangerous>true</IsDangerous>
      </DLLCheckData>
      <DLLCheckData>
        <DLLName>Hotkeys.dll</DLLName>
        <DLLVerifyInformation />
        <LatestSizeInBytes>0</LatestSizeInBytes>
        <IsDangerous>true</IsDangerous>
      </DLLCheckData>
      <DLLCheckData>
        <DLLName>MixMatch.dll</DLLName>
        <DLLVerifyInformation />
        <LatestSizeInBytes>0</LatestSizeInBytes>
        <IsDangerous>true</IsDangerous>
      </DLLCheckData>
      <DLLCheckData>
        <DLLName>ReticuleRepair.dll</DLLName>
        <DLLVerifyInformation />
        <LatestSizeInBytes>0</LatestSizeInBytes>
        <IsDangerous>true</IsDangerous>
      </DLLCheckData>
      <DLLCheckData>
        <DLLName>MolochsDuels.dll</DLLName>
        <DLLVerifyInformation />
        <LatestSizeInBytes>0</LatestSizeInBytes>
        <IsDangerous>true</IsDangerous>
      </DLLCheckData>
      <DLLCheckData>
        <DLLName>RenameAnySettlement.dll</DLLName>
        <DLLVerifyInformation />
        <LatestSizeInBytes>0</LatestSizeInBytes>
        <IsDangerous>true</IsDangerous>
      </DLLCheckData>
      <DLLCheckData>
        <DLLName>TournamentOfChampions.dll</DLLName>
        <DLLVerifyInformation />
        <LatestSizeInBytes>0</LatestSizeInBytes>
        <IsDangerous>true</IsDangerous>
      </DLLCheckData>
      <DLLCheckData>
        <DLLName>ArmyArrowCounter.dll</DLLName>
        <DLLVerifyInformation />
        <LatestSizeInBytes>0</LatestSizeInBytes>
        <IsDangerous>true</IsDangerous>
      </DLLCheckData>
      <DLLCheckData>
        <DLLName>Banner Fix.dll</DLLName>
        <DLLVerifyInformation />
        <LatestSizeInBytes>0</LatestSizeInBytes>
        <IsDangerous>true</IsDangerous>
      </DLLCheckData>
      <DLLCheckData>
        <DLLName>Homesteads.dll</DLLName>
        <DLLVerifyInformation />
        <LatestSizeInBytes>0</LatestSizeInBytes>
        <IsDangerous>true</IsDangerous>
      </DLLCheckData>
      <DLLCheckData>
        <DLLName>CommandFactionParties.dll</DLLName>
        <DLLVerifyInformation />
        <LatestSizeInBytes>0</LatestSizeInBytes>
        <IsDangerous>true</IsDangerous>
      </DLLCheckData>
      <DLLCheckData>
        <DLLName>ExpandCombatUI.dll</DLLName>
        <DLLVerifyInformation />
        <LatestSizeInBytes>0</LatestSizeInBytes>
        <IsDangerous>true</IsDangerous>
      </DLLCheckData>
      <DLLCheckData>
        <DLLName>BetterTroopHUD.dll</DLLName>
        <DLLVerifyInformation />
        <LatestSizeInBytes>0</LatestSizeInBytes>
        <IsDangerous>true</IsDangerous>
      </DLLCheckData>
      <DLLCheckData>
        <DLLName>Bannerlord.AssassinationMod.dll</DLLName>
        <DLLVerifyInformation />
        <LatestSizeInBytes>0</LatestSizeInBytes>
        <IsDangerous>true</IsDangerous>
      </DLLCheckData>
      <DLLCheckData>
        <DLLName>WealthyWorkshops.dll</DLLName>
        <DLLVerifyInformation />
        <LatestSizeInBytes>0</LatestSizeInBytes>
        <IsDangerous>true</IsDangerous>
      </DLLCheckData>
      <DLLCheckData>
        <DLLName>PlayerExecuteEdit.dll</DLLName>
        <DLLVerifyInformation />
        <LatestSizeInBytes>0</LatestSizeInBytes>
        <IsDangerous>true</IsDangerous>
      </DLLCheckData>
      <DLLCheckData>
        <DLLName>AIExecutioner.dll</DLLName>
        <DLLVerifyInformation />
        <LatestSizeInBytes>0</LatestSizeInBytes>
        <IsDangerous>true</IsDangerous>
      </DLLCheckData>
      <DLLCheckData>
        <DLLName>AIValuesLife.dll</DLLName>
        <DLLVerifyInformation />
        <LatestSizeInBytes>0</LatestSizeInBytes>
        <IsDangerous>true</IsDangerous>
      </DLLCheckData>
      <DLLCheckData>
        <DLLName>AllOneGender.dll</DLLName>
        <DLLVerifyInformation />
        <LatestSizeInBytes>0</LatestSizeInBytes>
        <IsDangerous>true</IsDangerous>
      </DLLCheckData>
      <DLLCheckData>
        <DLLName>ImmersiveTroops.dll</DLLName>
        <DLLVerifyInformation />
        <LatestSizeInBytes>0</LatestSizeInBytes>
        <IsDangerous>true</IsDangerous>
      </DLLCheckData>
      <DLLCheckData>
        <DLLName>OpposeClan.dll</DLLName>
        <DLLVerifyInformation />
        <LatestSizeInBytes>0</LatestSizeInBytes>
        <IsDangerous>true</IsDangerous>
      </DLLCheckData>
      <DLLCheckData>
        <DLLName>LT_Nemesis.dll</DLLName>
        <DLLVerifyInformation />
        <LatestSizeInBytes>0</LatestSizeInBytes>
        <IsDangerous>true</IsDangerous>
      </DLLCheckData>
      <DLLCheckData>
        <DLLName>FixMOD_majimie.dll</DLLName>
        <DLLVerifyInformation />
        <LatestSizeInBytes>0</LatestSizeInBytes>
        <IsDangerous>true</IsDangerous>
      </DLLCheckData>
      <DLLCheckData>
        <DLLName>ExpandKillLoot.dll</DLLName>
        <DLLVerifyInformation />
        <LatestSizeInBytes>0</LatestSizeInBytes>
        <IsDangerous>true</IsDangerous>
      </DLLCheckData>
      <DLLCheckData>
        <DLLName>Bannerlord.ModuleLoader.Bannerlord.EncyclopediaFilters.dll</DLLName>
        <DLLVerifyInformation />
        <LatestSizeInBytes>0</LatestSizeInBytes>
        <IsDangerous>true</IsDangerous>
      </DLLCheckData>
    </DLLData>
  </DLLCheckData>
  <AutomaticallyCheckForUpdates>false</AutomaticallyCheckForUpdates>
  <FixCommonIssues>false</FixCommonIssues>
  <CompactModuleList>false</CompactModuleList>
  <DisableBinaryCheck>false</DisableBinaryCheck>
  <HideRandomImage>false</HideRandomImage>
  <BetaSorting>false</BetaSorting>
  <BigMode>false</BigMode>
  <EnableDPIScaling>false</EnableDPIScaling>
  <DisableCrashHandlerWhenDebuggerIsAttached>false</DisableCrashHandlerWhenDebuggerIsAttached>
  <DisableCatchAutoGenExceptions>false</DisableCatchAutoGenExceptions>
  <UseVanillaCrashHandler>false</UseVanillaCrashHandler>
</UserData>