<?xml version="1.0" encoding="utf-8"?>
<GameKeyConfig xmlns:xsd="http://www.w3.org/2001/XMLSchema" xmlns:xsi="http://www.w3.org/2001/XMLSchema-instance">
  <Category>
    <CategoryId>RTSCameraHotKey</CategoryId>
    <GameKeySequences>
      <SerializedGameKeySequence>
        <StringId>Pause</StringId>
        <KeyboardKeys>
          <InputKey>OpenBraces</InputKey>
        </KeyboardKeys>
      </SerializedGameKeySequence>
      <SerializedGameKeySequence>
        <StringId>SlowMotion</StringId>
        <KeyboardKeys>
          <InputKey>Apostrophe</InputKey>
        </KeyboardKeys>
      </SerializedGameKeySequence>
      <SerializedGameKeySequence>
        <StringId>FreeCamera</StringId>
        <KeyboardKeys>
          <InputKey>F10</InputKey>
        </KeyboardKeys>
      </SerializedGameKeySequence>
      <SerializedGameKeySequence>
        <StringId>DisableDeath</StringId>
        <KeyboardKeys>
          <InputKey>End</InputKey>
        </KeyboardKeys>
      </SerializedGameKeySequence>
      <SerializedGameKeySequence>
        <StringId>ControlTroop</StringId>
        <KeyboardKeys>
          <InputKey>E</InputKey>
        </KeyboardKeys>
      </SerializedGameKeySequence>
      <SerializedGameKeySequence>
        <StringId>ToggleHUD</StringId>
        <KeyboardKeys>
          <InputKey>CloseBraces</InputKey>
        </KeyboardKeys>
      </SerializedGameKeySequence>
      <SerializedGameKeySequence>
        <StringId>SwitchTeam</StringId>
        <KeyboardKeys>
          <InputKey>F11</InputKey>
        </KeyboardKeys>
      </SerializedGameKeySequence>
      <SerializedGameKeySequence>
        <StringId>SelectCharacter</StringId>
        <KeyboardKeys>
          <InputKey>SemiColon</InputKey>
        </KeyboardKeys>
      </SerializedGameKeySequence>
      <SerializedGameKeySequence>
        <StringId>CameraMoveForward</StringId>
        <KeyboardKeys>
          <InputKey>W</InputKey>
        </KeyboardKeys>
      </SerializedGameKeySequence>
      <SerializedGameKeySequence>
        <StringId>CameraMoveBackward</StringId>
        <KeyboardKeys>
          <InputKey>S</InputKey>
        </KeyboardKeys>
      </SerializedGameKeySequence>
      <SerializedGameKeySequence>
        <StringId>CameraMoveLeft</StringId>
        <KeyboardKeys>
          <InputKey>A</InputKey>
        </KeyboardKeys>
      </SerializedGameKeySequence>
      <SerializedGameKeySequence>
        <StringId>CameraMoveRight</StringId>
        <KeyboardKeys>
          <InputKey>D</InputKey>
        </KeyboardKeys>
      </SerializedGameKeySequence>
      <SerializedGameKeySequence>
        <StringId>CameraMoveUp</StringId>
        <KeyboardKeys>
          <InputKey>Space</InputKey>
        </KeyboardKeys>
      </SerializedGameKeySequence>
      <SerializedGameKeySequence>
        <StringId>CameraMoveDown</StringId>
        <KeyboardKeys>
          <InputKey>Z</InputKey>
        </KeyboardKeys>
      </SerializedGameKeySequence>
      <SerializedGameKeySequence>
        <StringId>IncreaseCameraDistanceLimit</StringId>
        <KeyboardKeys>
          <InputKey>RightShift</InputKey>
          <InputKey>Equals</InputKey>
        </KeyboardKeys>
      </SerializedGameKeySequence>
      <SerializedGameKeySequence>
        <StringId>DecreaseCameraDistanceLimit</StringId>
        <KeyboardKeys>
          <InputKey>RightShift</InputKey>
          <InputKey>Minus</InputKey>
        </KeyboardKeys>
      </SerializedGameKeySequence>
    </GameKeySequences>
  </Category>
  <ConfigVersion>1.0</ConfigVersion>
</GameKeyConfig>